MANIFEST.in
NEWS.txt
README.rst
setup.py
auroch/__init__.py
auroch.egg-info/PKG-INFO
auroch.egg-info/SOURCES.txt
auroch.egg-info/dependency_links.txt
auroch.egg-info/entry_points.txt
auroch.egg-info/not-zip-safe
auroch.egg-info/top_level.txt
auroch/rclient/__init__.py
auroch/rclient/client.py
auroch/rclient/tests/__init__.py
auroch/rclient/tests/client_test.py
auroch/redis/__init__.py
auroch/redis/base.py
auroch/redis/dict.py
auroch/redis/pubsub.py
auroch/rserver/__init__.py
auroch/rserver/frontend.py
auroch/rserver/redisconnect.py
auroch/rserver/views.py